gendiff/__init__.py
gendiff/formaters.py
gendiff/gendiff_m.py
gendiff/scripts/__init__.py
gendiff/scripts/gendiff_s.py
hexlet_code_at_shiffter-0.1.0.dist-info/entry_points.txt
hexlet_code_at_shiffter-0.1.0.dist-info/WHEEL
hexlet_code_at_shiffter-0.1.0.dist-info/METADATA
hexlet_code_at_shiffter-0.1.0.dist-info/RECORD
