Metadata-Version: 2.1
Name: hexlet-code-at-shiffter
Version: 0.1.0
Summary: Generate diff
Author: shifter
Author-email: vanfre93@gmail.com.com
Requires-Python: >=3.8,<4.0
Classifier: Programming Language :: Python :: 3
Classifier: Programming Language :: Python :: 3.10
Classifier: Programming Language :: Python :: 3.8
Classifier: Programming Language :: Python :: 3.9
Requires-Dist: PyYAML (>=6.0,<7.0)
Requires-Dist: pytest-cov (>=3.0.0,<4.0.0)
